sae_dashboard/__init__.py
sae_dashboard/clt_layer_wrapper.py
sae_dashboard/components.py
sae_dashboard/components_config.py
sae_dashboard/css/dropdown.css
sae_dashboard/css/general.css
sae_dashboard/css/sequences.css
sae_dashboard/css/tables.css
sae_dashboard/data_parsing_fns.py
sae_dashboard/data_writing_fns.py
sae_dashboard/dfa_calculator.py
sae_dashboard/feature_data.py
sae_dashboard/feature_data_generator.py
sae_dashboard/html/acts_histogram_template.html
sae_dashboard/html/feature_tables_template.html
sae_dashboard/html/logits_histogram_template.html
sae_dashboard/html/logits_table_template.html
sae_dashboard/html/sequences_group_template.html
sae_dashboard/html_fns.py
sae_dashboard/js/_setupPageScript.js
sae_dashboard/js/actsHistogramScript.js
sae_dashboard/js/featureTablesScript.js
sae_dashboard/js/gridColumnTitlesScript.js
sae_dashboard/js/logitsHistogramScript.js
sae_dashboard/js/logitsTableScript.js
sae_dashboard/js/tokenScript.js
sae_dashboard/layout.py
sae_dashboard/neuronpedia/__init__.py
sae_dashboard/neuronpedia/generating_neuronpedia_outputs.ipynb
sae_dashboard/neuronpedia/neuronpedia_converter.py
sae_dashboard/neuronpedia/neuronpedia_dashboard.py
sae_dashboard/neuronpedia/neuronpedia_runner.py
sae_dashboard/neuronpedia/neuronpedia_runner_config.py
sae_dashboard/neuronpedia/neuronpedia_vector_runner.py
sae_dashboard/neuronpedia/vector_set.py
sae_dashboard/sae_vis_data.py
sae_dashboard/sae_vis_runner.py
sae_dashboard/sequence_data_generator.py
sae_dashboard/transformer_lens_wrapper.py
sae_dashboard/utils_fns.py
sae_dashboard/vector_data_generator.py
sae_dashboard/vector_vis_data.py
sae_dashboard/vector_vis_runner.py
sae_dashboard-0.7.3.dist-info/METADATA
sae_dashboard-0.7.3.dist-info/WHEEL
sae_dashboard-0.7.3.dist-info/entry_points.txt
sae_dashboard-0.7.3.dist-info/licenses/LICENSE
sae_dashboard-0.7.3.dist-info/RECORD
