Metadata-Version: 2.4
Name: sae-dashboard
Version: 0.7.3
Summary: Open-source SAE visualizer, based on Anthropic's published visualizer. Forked / Detached from sae_vis.
License: MIT
License-File: LICENSE
Author: Callum McDougall
Author-email: cal.s.mcdougall@gmail.com
Requires-Python: >=3.10,<4.0
Classifier: License :: OSI Approved :: MIT License
Classifier: Programming Language :: Python :: 3
Classifier: Programming Language :: Python :: 3.10
Classifier: Programming Language :: Python :: 3.11
Classifier: Programming Language :: Python :: 3.12
Classifier: Programming Language :: Python :: 3.13
Classifier: Programming Language :: Python :: 3.14
Requires-Dist: dataclasses-json (>=0.6.4,<0.7.0)
Requires-Dist: datasets (>=3.0.0,<4.0.0)
Requires-Dist: decode-clt (>=0.0.1,<0.0.2)
Requires-Dist: eindex-callum (>=0.1.0,<0.2.0)
Requires-Dist: einops (>=0.7.0)
Requires-Dist: hf-transfer (>=0.1.9,<0.2.0)
Requires-Dist: jaxtyping (>=0.2.28,<0.3.0)
Requires-Dist: matplotlib (>=3.8.4,<4.0.0)
Requires-Dist: rich (>=13.7.1,<14.0.0)
Requires-Dist: sae-lens (>=6.8.0,<7.0.0)
Requires-Dist: safetensors (>=0.4.3,<0.5.0)
Requires-Dist: torch (>=2.0.0,<3.0.0)
Requires-Dist: transformer-lens (>=2.2.0,<3.0.0)
Requires-Dist: transformers (<4.57.0)
Requires-Dist: typer (>=0.12.3,<0.13.0)
